routeros_diff/__init__.py
routeros_diff/arguments.py
routeros_diff/commands/__init__.py
routeros_diff/commands/diff.py
routeros_diff/commands/prettify.py
routeros_diff/exceptions.py
routeros_diff/expressions.py
routeros_diff/parser.py
routeros_diff/sections.py
routeros_diff/settings.py
routeros_diff/utilities.py
routeros_diff-0.5.3.dist-info/entry_points.txt
routeros_diff-0.5.3.dist-info/LICENSE.txt
routeros_diff-0.5.3.dist-info/WHEEL
routeros_diff-0.5.3.dist-info/METADATA
routeros_diff-0.5.3.dist-info/RECORD
