Metadata-Version: 2.1
Name: routeros-diff
Version: 0.5.3
Summary: Tools for parsing & diffing RouterOS configuration files. Can produce config file patches.
Home-page: https://github.com/gardunha/routeros-diff
License: MIT
Author: Adam Charnock
Author-email: adam.charnock@gardunha.net
Requires-Python: >=3.6,<4.0
Classifier: License :: OSI Approved :: MIT License
Classifier: Programming Language :: Python :: 3
Classifier: Programming Language :: Python :: 3.6
Classifier: Programming Language :: Python :: 3.7
Classifier: Programming Language :: Python :: 3.8
Classifier: Programming Language :: Python :: 3.9
Requires-Dist: python-dateutil (>=2.8.1,<3.0.0)
Project-URL: Repository, https://github.com/gardunha/routeros-diff
